LICENSE
README.md
setup.py
fuzzy_expert/__init__.py
fuzzy_expert/inference.py
fuzzy_expert/mf.py
fuzzy_expert/operators.py
fuzzy_expert/plots.py
fuzzy_expert/rule.py
fuzzy_expert/variable.py
fuzzy_expert.egg-info/PKG-INFO
fuzzy_expert.egg-info/SOURCES.txt
fuzzy_expert.egg-info/dependency_links.txt
fuzzy_expert.egg-info/requires.txt
fuzzy_expert.egg-info/top_level.txt
tests/__init__.py
tests/bank.py
tests/test_inference.py
tests/test_mf.py
tests/test_rule.py
tests/test_variable.py