Metadata-Version: 2.1
Name: fuzzy-expert
Version: 0.1.0
Summary: Fuzzy Expert System in Python
Home-page: http://github.com/jdvelasq/fuzzy-expert
Author: Juan D. Velasquez
Author-email: jdvelasq@unal.edu.co
License: MIT
Keywords: fuzzy
Platform: any
Classifier: Development Status :: 3 - Alpha
Classifier: License :: OSI Approved :: MIT License
Classifier: Intended Audience :: Science/Research
Classifier: Programming Language :: Python :: 3
Classifier: Programming Language :: Python :: 3.6
Classifier: Programming Language :: Python :: 3.5
Classifier: Programming Language :: Python :: 3.6
Classifier: Programming Language :: Python :: 3.7
Classifier: Programming Language :: Python :: 3.8
Provides: fuzzy_expert
License-File: LICENSE
